sqlite_orm/__init__.py
sqlite_orm/database.py
sqlite_orm/logger.py
sqlite_orm/manager.py
sqlite_orm/model.py
sqlite_orm/sqlite3.bin
sqlite_orm/vec0.so
sqlite_orm_vec_qpython-0.1.5.dist-info/METADATA
sqlite_orm_vec_qpython-0.1.5.dist-info/WHEEL
sqlite_orm_vec_qpython-0.1.5.dist-info/top_level.txt
sqlite_orm_vec_qpython-0.1.5.dist-info/RECORD
